{"title":"沈宝宝与二分图","time_limit":8000,"memory_limit":64,"url":"https://acm.uestc.edu.cn/problem/chen-bao-bao-yu-er-fen-tu/description","statement":[{"title":"Content","format":"markdown","require":["katex"],"content":"\n沈宝宝开始学习二分图啦\n\n现在沈宝宝有了一个二分图，沈宝宝想知道有多少种方法选择一个点集$D$\n\n使得整个二分图中的点，要么在$D$中，要么直接连着$D$\n"},{"title":"Standard Input","format":"markdown","require":["katex"],"content":"\n第一行两个整数$N,M$，表示有$N$个点，$M$条边，点从1开始编号\n\n接下来$M$行，每行两个整数$u,v$表示$u,v$之间有一条边\n\n输入保证没有重边自环，并且是个二分图\n\n$1\\le N \\le 30$\n\n$0\\le M \\le 225$\n"},{"title":"Standard Output","format":"markdown","require":["katex"],"content":"\n输出一个整数，表示选择点集的方案\n"},{"title":"Samples","format":"markdown","require":["katex"],"content":"\n<style>\n        table,table tr th, table tr td { border:1px solid #0094ff; }\n        table { width: 200px; min-height: 25px; line-height: 25px; text-align: center; border-collapse: collapse;}   \n    </style>\n<table>\n\t<tr>\n\t\t<td>Input</td>\n\t\t<td>Output</td>\n\t</tr>\n<tr><td>4 4\n1 2\n2 3\n3 4\n4 1</td><td>11</td></tr><tr><td>4 0</td><td>1</td></tr></table>\n\n"}]}