{"title":"平面上的二叉树","time_limit":3000,"memory_limit":256,"url":"https://acm.uestc.edu.cn/problem/ping-mian-shang-de-er-cha-shu/description","statement":[{"title":"Content","format":"markdown","require":["katex"],"content":"\n秦队长是一个天才，他经常有一些无敌的想法。\n一天，他在坐标纸上写写画画，发现一些点连接起来可以出现很美丽的图案。\n于是，作为英明神武的acm集训队队长，他想如果随机给出平面上一些点的坐标，能否用这些点连接成一棵二叉树，并且这棵二叉树的边权和最小。二叉树的边权就是两点之间的欧几里得距离。\n对于平面上的二叉树，所有的边都是自上而下的，就是对于一条边是从$u$到$v$，必然满足$u$的纵坐标严格大于$v$的纵坐标\n"},{"title":"Standard Input","format":"markdown","require":["katex"],"content":"\n第一行是一个$n$(2<=$n$<=400)表示平面上点的个数\n接下来的n行，每行两个整数$x_i、y_i (|x_i|,|y_i| <= 1e3)$，表示每个点的坐标\n"},{"title":"Standard Output","format":"markdown","require":["katex"],"content":"\n输出最小权值，结果保留6位小数，如果不存在满足要求的二叉树，那么输出$“-1”$。\n"},{"title":"Samples","format":"markdown","require":["katex"],"content":"\n<style>\n        table,table tr th, table tr td { border:1px solid #0094ff; }\n        table { width: 200px; min-height: 25px; line-height: 25px; text-align: center; border-collapse: collapse;}   \n    </style>\n<table>\n\t<tr>\n\t\t<td>Input</td>\n\t\t<td>Output</td>\n\t</tr>\n<tr><td>3\n0 0\n1 0\n2 1</td><td>3.650281539872885</td></tr></table>\n\n"}]}