{"title":"旋转单词","time_limit":1000,"memory_limit":125,"url":"http://www.joyoi.cn/problem/codevs-1552","statement":[{"title":"","format":"html_final","require":["katex"],"content":"\n<div class=\"panel panel-default\">\n<div class=\"area-title\">\n<span>\n题目描述\n<small>Description</small>\n</span></div>\n<div class=\"panel-body\">\n\n<p>    今天的英语课，王老师为了复习以前学过的单词，提高学生的学习兴趣，想出了一个主意：</p>\n<p>    读入M组数据，其中每组数据有一个单词L（单词长度≤36个字符）和一个整数N(1≤N≤36)，从该单词最末位开始逐位移到单词的开头，如果还没达到N值，则再从末位开始移动，直到达N值为止，求移N位后的新单词。你能编程帮助贝贝最快完成任务吗？</p>\n\n</div>\n</div>\n\n<div class=\"panel panel-default\">\n<div class=\"area-title\">\n<span>\n输入描述\n<small>Input Description</small>\n</span></div>\n<div class=\"panel-body\">\n<p>    文件共有2×M+I行，第1行为M，第2行开始为具体数据，每一组数据有2行，第1行字串L，第2行为N。</p>\n\n</div>\n</div>\n<div  class=\"panel panel-default\">\n<div class=\"area-title\">\n<span>\n输出描述\n<small>Output Description</small>\n</span></div>\n<div class=\"panel-body\">\n\n<p>&nbsp;&nbsp; &nbsp;共M行，每行为旋转后的字串。</p>\n\n</div>\n</div>\n\n\n<div class=\"panel panel-default\">\n<div class=\"area-title\">\n<span>\n样例输入\n<small>Sample Input</small>\n</span></div>\n<div class=\"panel-body\">\n<table border=\"1\" cellpadding=\"0\" cellspacing=\"0\">\n<tbody>\n<tr>\n<td width=\"139\">\n<p> </p>\n</td>\n<td width=\"188\">\n<p>输入</p>\n</td>\n<td width=\"188\">\n<p>输出</p>\n</td>\n</tr>\n<tr>\n<td width=\"139\">\n<p>样例1</p>\n</td>\n<td width=\"188\">\n<p>1</p>\n<p>computer</p>\n<p>3</p>\n</td>\n<td width=\"188\">\n<p>tercompu</p>\n</td>\n</tr>\n<tr>\n<td width=\"139\">\n<p>样例2</p>\n</td>\n<td width=\"188\">\n<p>1</p>\n<p>program</p>\n<p>1</p>\n</td>\n<td width=\"188\">\n<p>mprogra</p>\n</td>\n</tr>\n<tr>\n<td width=\"139\">\n<p>样例3</p>\n</td>\n<td width=\"188\">\n<p>1</p>\n<p>ABCDEFGH</p>\n<p>35</p>\n</td>\n<td width=\"188\">\n<p>FGHABCDE</p>\n</td>\n</tr>\n</tbody>\n</table>\n\n</div>\n</div>\n\n<div class=\"panel panel-default\">\n<div class=\"area-title\">\n<span>\n样例输出\n<small>Sample Output</small>\n</span></div>\n<div class=\"panel-body\">\n<p>在样例描述里</p>\n\n</div>\n</div>\n\n<div class=\"panel panel-default\">\n<div class=\"area-title\">\n<span>\n数据范围及提示\n<small>Data Size & Hint</small>\n</span></div>\n<div class=\"panel-body\">\n\n</div>\n</div>\n"}]}