{"title":"jb","time_limit":1000,"memory_limit":250,"url":"http://www.joyoi.cn/problem/codevs-5743","statement":[{"title":"","format":"html_final","require":["katex"],"content":"\n<div class=\"panel panel-default\">\n<div class=\"area-title\">\n<span>\n题目描述\n<small>Description</small>\n</span></div>\n<div class=\"panel-body\">\n\n<p>JB</p>\n\n</div>\n</div>\n\n<div class=\"panel panel-default\">\n<div class=\"area-title\">\n<span>\n输入描述\n<small>Input Description</small>\n</span></div>\n<div class=\"panel-body\">\n<p>JB</p>\n\n</div>\n</div>\n<div  class=\"panel panel-default\">\n<div class=\"area-title\">\n<span>\n输出描述\n<small>Output Description</small>\n</span></div>\n<div class=\"panel-body\">\n\n<p>JB</p>\n\n</div>\n</div>\n\n\n<div class=\"panel panel-default\">\n<div class=\"area-title\">\n<span>\n样例输入\n<small>Sample Input</small>\n</span></div>\n<div class=\"panel-body\">\n<p>JB</p>\n\n</div>\n</div>\n\n<div class=\"panel panel-default\">\n<div class=\"area-title\">\n<span>\n样例输出\n<small>Sample Output</small>\n</span></div>\n<div class=\"panel-body\">\n<p>JB</p>\n\n</div>\n</div>\n\n<div class=\"panel panel-default\">\n<div class=\"area-title\">\n<span>\n数据范围及提示\n<small>Data Size & Hint</small>\n</span></div>\n<div class=\"panel-body\">\n<p>JB</p>\n</div>\n</div>\n"}]}