{"title":"精明的会计","time_limit":1000,"memory_limit":0,"url":"http://www.joyoi.cn/problem/codevs-5918","statement":[{"title":"","format":"html_final","require":["katex"],"content":"\n<div class=\"panel panel-default\">\n<div class=\"area-title\">\n<span>\n题目描述\n<small>Description</small>\n</span></div>\n<div class=\"panel-body\">\n\n<p style=\"font-family: 'Helvetica Neue', Helvetica, Arial, sans-serif;\"><span style=\"\">农民约翰是一个惊人的会计，并意识到自己可能遇到了农场的资金周转不灵时期。他已经计算和记录了</span><span style=\"\">N</span><span style=\"\">天（</span><span style=\"\">1</span><span style=\"\">≤</span><span style=\"\">N</span><span style=\"\">≤</span><span style=\"\">1000</span><span style=\"\">）每一天需要花费资金的确切数额（</span><span style=\"\">1</span><span style=\"\">≤</span><span style=\"\">moneyi</span><span style=\"\">≤</span><span style=\"\">10000</span><span style=\"\">）。</span><span style=\"\"> </span></p><p style=\"font-family: 'Helvetica Neue', Helvetica, Arial, sans-serif;\"><span style=\"\">由于每天向别人支付花费是一件非常麻烦的事情，所以聪明的约翰把连续的几天打包成一个集合，最多Ｍ</span><span style=\"\"> (1 </span><span style=\"\">≤</span><span style=\"\"> M </span><span style=\"\">≤</span><span style=\"\"> N)</span><span style=\"\">个集合，每个集合付一次钱。这样就可以减少付钱的次数，当然总数是不变的。</span><span style=\"\"> </span></p><p><span style=\"\"><span style=\"\">       </span></span><span style=\"\">对于每种分配方式，存在一个评价系数</span><span style=\"\">level</span><span style=\"\">，</span><span style=\"\">level</span><span style=\"\">为每一次付出费用的最大值。当然了，</span><span style=\"\">level</span><span style=\"\">的值越小，约翰会越有成就感。你的任务是帮助约翰计算出这个最小值。</span></p><p><br></p>\n\n</div>\n</div>\n\n<div class=\"panel panel-default\">\n<div class=\"area-title\">\n<span>\n输入描述\n<small>Input Description</small>\n</span></div>\n<div class=\"panel-body\">\n<p style=\"font-family: 'Helvetica Neue', Helvetica, Arial, sans-serif;\"><span style=\"\">第一行输入两个整数<span style=\"\">N</span>和<span style=\"\">M</span></span></p><p style=\"font-family: 'Helvetica Neue', Helvetica, Arial, sans-serif;\"><span style=\"\">接下来按顺序输入每一天需要花费资金的数额。</span></p><p><br></p>\n\n</div>\n</div>\n<div  class=\"panel panel-default\">\n<div class=\"area-title\">\n<span>\n输出描述\n<small>Output Description</small>\n</span></div>\n<div class=\"panel-body\">\n\n<p><span style=\"font-family: 宋体; font-size: 18px; background-color: rgb(238, 238, 238);\">输出</span><span style=\"box-sizing: border-box; font-family: 宋体; font-size: 18px; background-color: rgb(238, 238, 238);\">level</span><span style=\"font-family: 宋体; font-size: 18px; background-color: rgb(238, 238, 238);\">的最小值。</span></p>\n\n</div>\n</div>\n\n\n<div class=\"panel panel-default\">\n<div class=\"area-title\">\n<span>\n样例输入\n<small>Sample Input</small>\n</span></div>\n<div class=\"panel-body\">\n<p>   </p><pre style='font-family: Menlo, Monaco, Consolas, \"Courier New\", monospace;'>7 5\n100\n400\n300\n100\n500\n101\n400</pre><p><br></p>\n\n</div>\n</div>\n\n<div class=\"panel panel-default\">\n<div class=\"area-title\">\n<span>\n样例输出\n<small>Sample Output</small>\n</span></div>\n<div class=\"panel-body\">\n<p>   </p><pre style='font-family: Menlo, Monaco, Consolas, \"Courier New\", monospace;'>500</pre><p><br></p>\n\n</div>\n</div>\n\n<div class=\"panel panel-default\">\n<div class=\"area-title\">\n<span>\n数据范围及提示\n<small>Data Size & Hint</small>\n</span></div>\n<div class=\"panel-body\">\n<p>无</p>\n</div>\n</div>\n"}]}