{"title":"查找最大字符","time_limit":1000,"memory_limit":1,"url":"http://www.joyoi.cn/problem/codevs-3654","statement":[{"title":"","format":"html_final","require":["katex"],"content":"\n<div class=\"panel panel-default\">\n<div class=\"area-title\">\n<span>\n题目描述\n<small>Description</small>\n</span></div>\n<div class=\"panel-body\">\n\n<p>首先，输入n，表示将要输入的字符串总数。紧接着，输入n组字符串。在字符串中最大的字符后面添加（max）以ascii码为准。若出现多个，则各添加一个。</p><p>如：abcdeabcd  abcde(max)abcd</p><p>    xxx  x(max)x(max)x(max)</p>\n\n</div>\n</div>\n\n<div class=\"panel panel-default\">\n<div class=\"area-title\">\n<span>\n输入描述\n<small>Input Description</small>\n</span></div>\n<div class=\"panel-body\">\n<p>第一行：n行字符串</p><p>接下来n行：字符串<br></p>\n\n</div>\n</div>\n<div  class=\"panel panel-default\">\n<div class=\"area-title\">\n<span>\n输出描述\n<small>Output Description</small>\n</span></div>\n<div class=\"panel-body\">\n\n<p>输出添加了（max）的字符串<br/></p>\n\n</div>\n</div>\n\n\n<div class=\"panel panel-default\">\n<div class=\"area-title\">\n<span>\n样例输入\n<small>Sample Input</small>\n</span></div>\n<div class=\"panel-body\">\n<p>2</p><p>abcda</p><p>xccx</p>\n\n</div>\n</div>\n\n<div class=\"panel panel-default\">\n<div class=\"area-title\">\n<span>\n样例输出\n<small>Sample Output</small>\n</span></div>\n<div class=\"panel-body\">\n<p>abcd(max)a</p><p>x(max)ccx(max)</p>\n\n</div>\n</div>\n\n<div class=\"panel panel-default\">\n<div class=\"area-title\">\n<span>\n数据范围及提示\n<small>Data Size & Hint</small>\n</span></div>\n<div class=\"panel-body\">\n<p>n为1-100内的整数</p><p>字符串长度不超过100<br></p>\n</div>\n</div>\n"}]}