{"title":"短","time_limit":1000,"memory_limit":9,"url":"http://cogs.pro:8080/cogs/problem/problem.php?pid=vNymykakq","statement":[{"title":"题目描述","format":"html","require":["katex"],"content":"\n\n<h1>\n\tProblem C. 短\n</h1>\n给出无向图G = (V, E),求点V1 和点VN 之间的最短路。<br/>\n<h3>\n\tInput Specification\n</h3>\n第1行,2个整数|V |和|E|。<br/>\n第2行到第|E| + 1行,3个整数xi ,yi ,zi ,表示点Vxi 和点Vyi 之间存在权值为wi 的边。<br/>\n<h3>\n\tOutput Specification\n</h3>\n第1行,1个整数,表示最短路的权值。<br/>\n<h3>\n\tInput and Output Sample\n</h3>\nduan.in<br/>\n3<br/>\n1<br/>\n2<br/>\n3<br/>\n3<br/>\n2 1<br/>\n3 1<br/>\n1 1<br/>\nduan.out<br/>\n1<br/>\n<h3>\n\tData Restriction\n</h3>\n对于50%的数据,N ≤ 1, 000。<br/>\n对于100%的数据,N ≤ 100, 000, M ≤ 1, 000, 000, 1 ≤ Wi ≤ 2。<br/>\n<div>\n\t<br/>\n</div>\n\n"}]}