{"title":"数列操作B","time_limit":1000,"memory_limit":128,"url":"http://cogs.pro:8080/cogs/problem/problem.php?pid=vSzymkjke","statement":[{"title":"题目描述","format":"html","require":["katex"],"content":"\n\n<h3>\n【问题描述】\n</h3>\n<p>\n假设有一个大小为 $n(n≤100000)$ 整数数列 $A$，支持如下两种操作：\n</p>\n<p>\n1. 将 $A_i,A_{i+1},\\dots,A j$ 的值均增加 $d$\n</p>\n<p>\n2. 查询 $A_i$ 的值\n</p>\n<p>\n根据操作要求进行正确操作并输出结果。\n</p>\n<h3>\n【输入格式】\n</h3>\n<p>\n输入文件第一行一个整数 $n$，\n</p>\n<p>\n第二行为 $n$ 个整数，表示数列 $A$ 中各项的初始值。\n</p>\n<p>\n第三行为一个整数 $m$ ，表示操作数。下接 $m$ 行，每行描述一个操作，有如下两种情况：\n</p>\n<p>\nADD i j d（将 $A_i,A_{i+1},\\dots,A_j(1≤i,j≤n)$ 的值均增加一个整数 $d$）\n</p>\n<p>\nQUERY s（表示查询 $A_s$ 的值）\n</p>\n<h3>\n【输出格式】\n</h3>\n<p>\n对于每一个询问，输出查询到的结果。\n</p>\n<h3>\n【样例输入】\n</h3>\n<pre>4\n1 4 2 3\n3\nQUERY 1\nADD 2 2 50\nQUERY 2\n</pre>\n<h3>\n【样例输出】\n</h3>\n<pre>1\n54\n</pre>\n\n"}]}