{"title":"[USACO Mar]提高速度","time_limit":1000,"memory_limit":256,"url":"http://cogs.pro:8080/cogs/problem/problem.php?pid=vXNSmkqga","statement":[{"title":"# 题目描述","format":"html","require":["katex"],"content":"\n\n<h3>\n【题目描述】\n</h3>\n<p>\n<br/>\n</p>\n<p>\nBessie在为即将来临的汽车大赛准备赛车，它想购买一些附加装备来增强赛车的性能。赛车当前的质量为M(1≤M≤1，000)，具有F (1≤F≤1,000，000)大小的动力。商店里有N(1≤N≤10，000)个装备，编号1…N。Bessie可以随便购买多少个装备，但每个装备只能买一件。\n</p>\n<p>\n装备P_i可以增加F_i (1≤F_i≤1,000，000)的动力，但同时也增加了M_i(1≤M_i≤1,000)的质量。牛顿第二定律说：F=MA，F是力，M是质量，A是加速度。如果Bessie希望赛车的加速度最大(否则的话希望赛车的质量最轻)，那么它应当购买多少附加装备呢?\n</p>\n<p>\n例如，一辆赛车的初始值为F=1500，M=100，有4种附加装备：\n</p>\n<p>\ni F_i M_i\n</p>\n<p>\n1 250 25\n</p>\n<p>\n2 150 9\n</p>\n<p>\n3 120 5\n</p>\n<p>\n4 200 8\n</p>\n<p>\n如果只购买装备2，加速度为：(1500+150)/(100+9)=165/109=15.13761。\n</p>\n<p>\n下表列出了购买装备的各种组合情况，在第1列中，1表示要买，0表示不买。\n</p>\n<p>\nParts Aggregate Aggregate\n</p>\n<p>\n1234 F M F/M\n</p>\n<p>\n0000 1500 100 15.0000\n</p>\n<p>\n0001 1700 108 15.7407\n</p>\n<p>\n0010 1620 105 15.4286\n</p>\n<p>\n001 1 1820 113 16.1062\n</p>\n<p>\n0100 1650 109 15.1376\n</p>\n<p>\n0101 1850 117 15.8120\n</p>\n<p>\n0110 1770 114 15.5263\n</p>\n<p>\n011 1 1970 122 16.1475&lt;-最大的F/M\n</p>\n<p>\n1000 1750 125 14.0000\n</p>\n<p>\n1001 1950 133 14.6617\n</p>\n<p>\n1010 1870 130 14.3846\n</p>\n<p>\n1011 2070 138 15.0000\n</p>\n<p>\n1100 1900 134 14.179l\n</p>\n<p>\n1101 2100 142 14.7887\n</p>\n<p>\n1110 2020 139 14.5324\n</p>\n<p>\n1111 2220 147 15.1020\n</p>\n<p>\n因此，最佳的购买方案是2，3，4。\n</p>\n<p>\n<br/>\n</p>\n<h3>\n【输入格式】\n</h3>\n<p>\n<br/>\n</p>\n<p>\n第1行：3个整数F，M，N\n</p>\n<p>\n第2…N+I行：第i+l行包含2个整数F_i和M_i\n</p>\n<p>\n<br/>\n</p>\n<h3>\n【输出格式】\n</h3>\n<p>\n<br/>\n</p>\n<p>\n若干行，每行输出一个要购买的装备的编号，以升序输出。如果不需要购买，则输出&#39;NONE&#39;(不要引号)。\n</p>\n<p>\n数据保证答案唯一。\n</p>\n<p>\n<br/>\n</p>\n<h3>\n【样例输入】\n</h3>\n<pre>1500 100 4\n250 25\n150 9\n120 5\n200 8</pre>\n<h3>\n【样例输出】\n</h3>\n<pre>2\n3\n4</pre>\n<h3>\n【提示】\n</h3>\n<p>\n在此键入。\n</p>\n<h3>\n【来源】\n</h3>\n<p>\n在此键入。\n</p>\n\n"}]}