{"title":"[UVa 1482] 取石子游戏","time_limit":1000,"memory_limit":256,"url":"http://cogs.pro:8080/cogs/problem/problem.php?pid=vQNNJkqUg","statement":[{"title":"# 题目描述","format":"html","require":["katex"],"content":"\n\n<h3>\n【题目描述】\n</h3>\n<p>\n你和小伙伴在玩一个游戏，这个游戏是轮流从若干堆中拿石子。最初有N堆石子，每堆石子的个数是a1,a2，...,aN。每个回合，轮到的玩家必须从某堆石子中拿出至少一个石子，但拿的石子数不能超过这一堆石子数的一半。不能拿石子的玩家就输了。例如，有三堆石子，每堆分别有5,1,2个，那么玩家可以从第一堆中拿走1或2个石子，不能从第二堆中拿石子，可以从第三堆中拿走1个石子。注意，玩家不能从第二堆中拿石子的原因是1比1（该堆石子数量）的一半大。假定你先拿，并且你的朋友总是执行最佳策略，判断你是否有必胜策略。\n</p>\n<h3>\n【输入格式】\n</h3>\n<p>\n输入包含多组数据。\n</p>\n<p>\n输入文件的第1行有一个正整数T(1&lt;=T&lt;=100)，表示数据组数。\n</p>\n<p>\n接下来是T组数据。\n</p>\n<p>\n每组数据的第1行有一个正整数N(1&lt;=N&lt;=100)，表示堆数。\n</p>\n<p>\n每组数据的第2行有N个正整数a1,a2,...,aN(1&lt;=ai&lt;=2*10^18)，表示每堆的石子数。\n</p>\n<h3>\n【输出格式】\n</h3>\n<p>\n对每组数据，若你有必胜策略则输出一行&#34;YES&#34;，否则输出一行&#34;NO&#34;（均不带引号）。\n</p>\n<h3>\n【样例输入】\n</h3>\n<pre>4\n2\n4 4\n3\n1 2 3\n3\n2 4 6\n3\n1 2 1\n</pre>\n<h3>\n【样例输出】\n</h3>\n<pre>NO\nYES\nNO\nYES</pre>\n<h3>\n【来源】\n</h3>\n<p>\n<a href=\"http://uva.onlinejudge.org/index.php?option=com_onlinejudge&amp;Itemid=8&amp;category=477&amp;page=show_problem&amp;problem=4228\" target=\"_blank\">UVa 1482 Playing With Stones</a> \n</p>\n<p>\n刘汝佳，《算法竞赛入门经典训练指南》表2.6\n</p>\n\n"}]}