{"title":"[POJ2479+2593][NOIP2015初赛]双子序列最大和","time_limit":1000,"memory_limit":256,"url":"http://cogs.pro:8080/cogs/problem/problem.php?pid=vSXyyVaqa","statement":[{"title":"题目描述","format":"html","require":["katex"],"content":"\n\n<p>\n    给定一个长度为n（3 ≤ n ≤ 100000）的整数序列，要求从中选出两个连续子序列，使得这两个连续子序列的序列和之和最大，最终只需输出这个最大和。一个连续子序列的序列和为该连续子序列中所有数之和。要求：每个连续子序列长度至少为1，且两个连续子序列之间至少间隔1个数\n</p>\n<p>\n样例输入：\n</p>\n<p>\n3\n</p>\n<p>\n1 2 3\n</p>\n<p>\n样例输出\n</p>\n<p>\n4\n</p>\n<p>\n数据范围：\n</p>\n<p>\n对于30%的数据n&lt;=100\n</p>\n<p>\n对于50%的数据n&lt;=5*10^4\n</p>\n<p>\n对于100%的数据n&lt;=10^5\n</p>\n<p>\n来源：\n</p>\n<p>\nNOIP2015补充程序第一题\n</p>\n\n"}]}