{"title":"[UVA 11163]豹王","time_limit":3000,"memory_limit":128,"url":"http://cogs.pro:8080/cogs/problem/problem.php?pid=vzSSQVkej","statement":[{"title":"题目描述","format":"html","require":["katex"],"content":"\n\n<h3>\n【题目描述】\n</h3>\n<div class=\"ptx\" lang=\"zh-CN\">\n<p>\n在森林的深处，一场战争即将开始。像其他生物一样，猎豹们正在准备最后的战斗。他们不仅强壮，跑的比谁都快，他们还有一位智慧且勇敢的豹♂王（长者）。\n</p>\n<p>\n长者知道仅凭强壮和速度是无法赢得战争的。他们需要完美的编队。现在有N只豹子，豹王编号为1，其他的豹子编号为2到N，现在这N只豹子站成了一行。豹王认为，最优的编队应该是所有的豹子按编号顺序从小到大（1..N)站成一行。豹王可以通过交换自己和其他豹子的位置对队列进行调整，但可以与豹王交换位置的豹子会随豹王位置的改变而改变。\n</p>\n<p>\n设豹王的位置为i\n</p>\n<p>\n如果（i%4==1） 豹王可以和(i+1), (i+3), (i+4), (i-4)位置上的豹子交换。\n</p>\n<p>\n如果（i%4==2） 豹王可以和(i+1), (i-1), (i+4), (i-4)位置上的豹子交换。\n</p>\n<p>\n如果（i%4==3） 豹王可以和(i+1), (i-1), (i+4), (i-4)位置上的豹子交换。\n</p>\n<p>\n如果（i%4==0） 豹王可以和(i-3), (i-1), (i+4), (i-4)位置上的豹子交换。\n</p>\n<p>\n可以与豹王交换的豹子的位置显然应该在1到N之间。\n</p>\n<p>\n我们现在想知道最少要交换几次才能使编队最优\n</p>\n</div>\n<h3>\n【输入格式】\n</h3>\n<div class=\"ptx\" lang=\"zh-CN\">\n<p>\n多组数据。\n</p>\n<p>\n每组数据的第一行为N（1&lt;=N&lt;=40,N保证为4的倍数）。\n</p>\n<p>\n之后有N个整数，描述最初这N只豹子的排列顺序。\n</p>\n<p>\n输入文件结尾有一个0；\n</p>\n</div>\n<h3>\n【输出格式】\n</h3>\n<div class=\"ptx\" lang=\"zh-CN\">\n对于每组数据，输出最少的交换次数<br/>\n</div>\n<h3>\n【样例输入】\n</h3>\n<pre class=\"sio\">4\n1 2 3 4\n4\n4 2 3 1\n8\n5 2 3 4 8 6 7 1\n8\n5 2 8 3 6 7 1 4\n0\n</pre>\n<h3>\n【样例输出】\n</h3>\n<pre class=\"sio\">0\n1\n2\n7\n</pre>\n<h3>\n【提示】\n</h3>\n<p>\n<br/>\n</p>\n<h3>\n【来源】\n</h3>\n<h3>\n【题目来源】\n</h3>\n<p>\n<a href=\"https://uva.onlinejudge.org/index.php?option=com_onlinejudge&amp;Itemid=8&amp;category=23&amp;page=show_problem&amp;problem=2104\" target=\"_blank\">UVA11163</a> \n</p>\n\n"}]}