{"title":"[USACO Dec15]卡牌游戏(白金组)","time_limit":1000,"memory_limit":256,"url":"http://cogs.pro:8080/cogs/problem/problem.php?pid=vXzSyVVaa","statement":[{"title":"题目描述","format":"html","require":["katex"],"content":"\n\n<h3>\n【题目描述】\n</h3>\n<p>\n奶牛贝茜是卡牌游戏的狂热爱好者，但是令人吃惊的，她缺乏对手。不幸的是，任何牧群里的其他牛都不是好对手。\n</p>\n<p>\n他们实在是太差了，实际上，他们玩卡牌游戏时会遵循一种完全可以被预测的模式。然而对于贝茜来说，找到赢的方法仍然是一个挑战。\n</p>\n<p>\n贝茜和他的朋友埃尔西最近在玩一个简单的卡牌游戏，总共有$2N$张卡牌，上面的数字为$1-2N$, 贝茜分得$N$张，埃尔西分得$N$张。\n</p>\n<p>\n他们玩$N$局游戏，每局游戏双方都出一张牌。\n</p>\n<p>\n最初，数字大的得1分，输了不得分。但是，贝茜可以在游戏的某个时刻改变游戏规则（有且仅有一次），对于剩下的游戏，数字小的得1分，输了不得分。贝茜可以不做出这个选择，整局都是“高分卡片赢”，或者一开始就改变规则“低分卡片赢”。\n</p>\n<p>\n给出贝茜预测的埃尔西将要使用的$N$张卡片，求出贝茜的得分最大值。\n</p>\n<h3>\n【输入格式】\n</h3>\n<p>\n第一行一个整数$n$\n</p>\n<p>\n接下来$n$行每行一个整数$x$,表示埃尔西拥有的卡片数字\n</p>\n<p>\n很简单就能推测出贝茜拥有的卡片\n</p>\n<h3>\n【输出格式】\n</h3>\n<p>\n只有一行一个整数$max$,为得分最大值\n</p>\n<h3>\n【样例输入】\n</h3>\n<p>\n4\n</p>\n<p>\n1\n</p>\n<p>\n8\n</p>\n<p>\n4\n</p>\n<p>\n3\n</p>\n<h3>\n【样例输出】\n</h3>\n<p>\n3\n</p>\n<h3>\n【提示】\n</h3>\n<p>\n这里，贝茜一定拥有卡片2,5,6,7,最多可以赢3分\n</p>\n<p>\n以下是两种（不止两种3分方案）\n</p>\n<p>\n     Elsie Bessie  Bessie Score\n</p>\n<p>\n      1   &lt;  2          1\n</p>\n<p>\n     8   &gt;  5          0\n</p>\n<p>\n     4   &lt;  6          1\n</p>\n<p>\n     3   &lt;  7          1\n</p>\n<p>\n     no change rules(一直大者得分)\n</p>\n<p>\n<br/>\n</p>\n<p>\n Elsie Bessie  Bessie Score\n</p>\n<p>\n    刚开始大者得分\n</p>\n<p>\n    1   &lt;  7          1\n</p>\n<p>\n    change rules(从此之后小者得分)\n</p>\n<p>\n    8   &gt;  6          1\n</p>\n<p>\n    4   &gt;  2          1\n</p>\n<p>\n    3   &lt;  5          0     no change rules\n</p>\n<p>\n<br/>\n</p>\n<p>\n对于13%的数据，$n&lt;=100$\n</p>\n<p>\n对于20%的数据, $n&lt;=20000$\n</p>\n<p>\n对于100%的数据,$n&lt;=50000$\n</p>\n<h3>\n【来源】\n</h3>\n<p>\nUSACO 2015 Dec HighCard Lowcard (Platinum)\n</p>\n\n"}]}