{"title":"游戏_","time_limit":1000,"memory_limit":256,"url":"http://cogs.pro:8080/cogs/problem/problem.php?pid=vQQQSVeak","statement":[{"title":"# 题目描述","format":"html","require":["katex"],"content":"\n\n<h3>\n【题目描述】\n</h3>\n<p>\n<br/>\n</p>\n<p>\n<strong>Cindy 和 Dan 在玩一个游戏。初始 Cindy 把 n 个数给 Dan，然后开始游戏：</strong> \n</p>\n<p>\n<strong>每次 Dan 得到一组数后，他会把所有的数加起来，然后把总和加入到分数</strong> \n</p>\n<p>\n<strong>当中。然后他就把这组数给回 Cindy。</strong> \n</p>\n<p>\n<strong>每次 Cindy 得到一组数后，如果这组数只有一个，那么她会把它扔掉；如果</strong> \n</p>\n<p>\n<strong>这组数多于一个，她会把这组数分成两组（每组至少有一个数） ，然后把它们分</strong> \n</p>\n<p>\n<strong>别给回 Dan。</strong> \n</p>\n<p>\n<strong>每次游戏结束后他们特别关心自己的分数。他们想知道对于一组数，能得到</strong> \n</p>\n<p>\n<strong>的最大的得分是多少？</strong> \n</p>\n<p>\n<br/>\n</p>\n<p>\n<br/>\n</p>\n<h3>\n【输入格式】\n</h3>\n<p>\n<br/>\n</p>\n<p>\n<strong>第一行一个正整数 n，代表一开始数的个数；</strong> \n</p>\n<p>\n<strong>第二行 n 个正整数，代表这 n 个整数是什么。</strong> \n</p>\n<p>\n<br/>\n</p>\n<p>\n<br/>\n</p>\n<h3>\n【输出格式】\n</h3>\n<p>\n一行一个整数，代表可能的最大得分。\n</p>\n<h3>\n【样例输入】\n</h3>\n<pre><p>\n3\n</p>\n\n<p>\n3 1 5\n</p>\n\n<p>\n<br/>\n\n</p>\n</pre>\n<h3>\n【样例输出】\n</h3>\n<pre>26</pre>\n<h3>\n【提示】\n</h3>\n<p>\n<br/>\n</p>\n<p>\n对于样例，一开始 Cindy 把[3, 1, 5]给 Dan，Dan 向总分加上 3 + 1 + 5；Dan\n</p>\n<p>\n把[3, 1, 5]给回 Cindy，Cindy 把它分成两组数[3, 5]和[1]，再给回 Dan，Dan 得\n</p>\n<p>\n到[1]后往总分加上 1 并把[1]给回 Cindy， Cindy 在得到后把它扔掉； Dan 得到[3,\n</p>\n<p>\n5]后往总分加上 3 + 5，再给回 Cindy。Cindy 最后把[3, 5]分成[3]和[5]，Dan 在\n</p>\n<p>\n总分分别加上 3 和 5.最后他们的总分是 9 + 1 + 8 + 3 + 5 = 26.\n</p>\n<p>\n<br/>\n</p>\n<p>\n<br/>\n</p>\n<p>\n<br/>\n</p>\n<p>\n对于 30%的数据，N&lt;=5;\n</p>\n<p>\n对于 60%的数据，N&lt;=1000;\n</p>\n<p>\n对于 100%的数据，N&lt;=100000;\n</p>\n<p>\n所有的数权值小于 1000000.\n</p>\n<p>\n<br/>\n</p>\n<p>\n<br/>\n</p>\n<p>\n<br/>\n</p>\n<h3>\n【来源】\n</h3>\n<p>\n清北学堂寒假基础班模拟\n</p>\n\n"}]}