{"title":"[Codeforces 827A] 字串重组","time_limit":1000,"memory_limit":256,"url":"http://cogs.pro:8080/cogs/problem/problem.php?pid=vxJNxVWga","statement":[{"title":"题目描述","format":"html","require":["katex"],"content":"\n\n<h3>\n【题目描述】\n</h3>\n<p>\n 求一个<strong>字典序最小</strong>字串S。根据已知的一些子串在其中出现的次数和位置。\n</p>\n<h3>\n【输入格式】\n</h3>\n<p>\n第一行一个整数n(1 ≤ n ≤ 10^5) — 已知子串的数目。\n</p>\n<p>\n接下来n行是这些子串的信息。第i行包含子串ti，和正整数ki（表示ti在s中出现次数）,然后有升序排列的ki个正整数表示ti在s中出现位置。保证ti长度之和不超过10^6，且ki之和不超过10^6+2。 子串ti可以<strong>相同</strong>.\n</p>\n<p>\n保证数据不会自相矛盾,因此至少存在一个答案。\n</p>\n<p>\n数据字符集为小写字母\n</p>\n<h3>\n【输出格式】\n</h3>\n<p>\n输出<strong>字典序最小</strong> 的满足条件的字串s。\n</p>\n<h3>\n【样例输入1】\n</h3>\n<p>\n<br/>\n</p>\n<p>\n3\n</p>\n<p>\na 4 1 3 5 7\n</p>\n<p>\nab 2 1 5\n</p>\n<p>\nca 1 4\n</p>\n<p>\n<br/>\n</p>\n<h3>\n【样例输出1】\n</h3>\n<p>\n abacaba\n</p>\n<h3>\n【样例输入2】\n</h3>\n<p>\n1\n</p>\n<p>\na 1 3\n</p>\n<h3>\n【样例输出2】\n</h3>\n<p>\n aaa\n</p>\n<h3>\n【样例输入3】\n</h3>\n<p>\n3\n</p>\n<p>\nab 1 1\n</p>\n<p>\naba 1 3\n</p>\n<p>\nab 2 3 5\n</p>\n<h3>\n【样例输出3】\n</h3>\n<p>\n ababab\n</p>\n<h3>\n【来源】\n</h3>\n<p>\n<u><strong>CodeForces</strong></u> \n</p>\n<p>\n<a href=\"http://codeforces.com/contest/827/problem/A\" target=\"_blank\">http://codeforces.com/contest/827/problem/A</a> \n</p>\n<p>\n<br/>\n</p>\n\n"}]}