{"title":"[UVa 116] 单向 TSP","time_limit":1000,"memory_limit":256,"url":"http://cogs.pro:8080/cogs/problem/problem.php?pid=vmNiSVUka","statement":[{"title":"题目描述","format":"html","require":["katex"],"content":"\n\n<h3>\n【题目描述】\n</h3>\n<p>\n给一个m*n的矩阵(m&lt;=10,n&lt;=100),从第一列任何一个位置出发每次向右或右上或右下走一格第一行的上一行是最后一行 最后一行的下一行是第一行\n</p>\n<p>\n求从第一列到第n列权值总和最小路径并输出字典序最小的方案\n</p>\n<h3>\n【输入格式】\n</h3>\n<p>\n第一行2个整数m,n\n</p>\n<p>\n第2到m+1行 每行n个整数表示权值\n</p>\n<h3>\n【输出格式】\n</h3>\n<p>\nn个整数 输出路径上每列行号\n</p>\n<p>\n接下来一个整数最小权值\n</p>\n<h3>\n【样例输入】\n</h3>\n<pre>7 3\n26 78 12\n1 29 5\n2 98 40\n47 13 78\n38 72 67\n39 32 15\n36 39 64\n</pre>\n<h3>\n【样例输出】\n</h3>\n<pre>2 2 2\n35\n</pre>\n<h3>\n【提示】\n</h3>\n<p>\n在此键入。\n</p>\n<h3>\n【来源】\n</h3>\n<p>\nUVa 116 Unidirectional TSP\n</p>\n\n"}]}