{"title":"奖金","time_limit":1000,"memory_limit":256,"url":"http://cogs.pro:8080/cogs/problem/problem.php?pid=vXmxmjaPj","statement":[{"title":"题目描述","format":"html","require":["katex"],"content":"\n\n<h3>\n【题目描述】\n</h3>\n<p>\n由于无敌的凡凡在2005年世界英俊帅气男总决选中胜出，Yali Company总经理Mr.Z心情好，决定给每位员工发奖金。公司决定以每个人本年在公司的贡献为标准来计算他们得到奖金的多少。于是Mr.Z下令召开m方会谈。每位参加会谈的代表提出了自己的意见：“我认为员工a的奖金应该比b高！”Mr.Z决定要找出一种奖金方案，满足各位代表的意见，且同时使得总奖金数最少。每位员工奖金最少为100元。 \n</p>\n<h3>\n【输入格式】\n</h3>\n<p>\n第一行两个整数n,m，表示员工总数和代表数；以下m行，每行2个整数a,b，表示某个代表认为第a号员工奖金应该比第b号员工高。\n</p>\n<h3>\n【输出格式】\n</h3>\n<p>\n若无法找到合理方案，则输出“Poor Xed”；否则输出一个数表示最少总奖金。\n</p>\n<h3>\n【样例输入】\n</h3>\n<p>\n2 1\n</p>\n<p>\n1 2\n</p>\n<h3>\n【样例输出】\n</h3>\n<p>\n201\n</p>\n<h3>\n【提示】\n</h3>\n<p>\nn&lt;=1e4\n</p>\n<h3>\n【来源】\n</h3>\n<p>\n在此键入。\n</p>\n\n"}]}