{"title":"(USACO Dec18)平衡木","time_limit":1000,"memory_limit":256,"url":"http://cogs.pro:8080/cogs/problem/problem.php?pid=vmSyQjkqa","statement":[{"title":"# 题目描述","format":"html","require":["katex"],"content":"\n\n<h3>\n【题目描述】\n</h3>\n<p>\n(译者：Satoshi, 转载请注明出处)\n</p>\n<p>\n<img src=\"/upload/image/20190513/20190513120500_92411.jpg\" alt=\"\" title=\"\" width=\"750\" height=\"500\" align=\"\"/> \n</p>\n<p>\n为了给谷仓的新畜栏省钱，奶牛贝茜开始在当地的杂戏团表演。通过在很高的平衡木上来回走动来展现她非凡的平衡感。\n</p>\n<p>\n贝茜每次赚多少钱跟她在最终在平衡木的哪一个位置跳下来有关。平衡木从左到右的位置标为$0,1,..., N+1$。如果贝茜到达了位置$0$或者位置$N+1$她就会从平衡木的一端掉下来并且（很悲伤的）赚不到一分钱。\n</p>\n<p>\n如果贝茜在一个给定的位置k, 她可以做下面两件事中的一件：\n</p>\n<p>\n1. 投掷一枚硬币。如果是反面，贝茜移动到位置$k-1$；如果是正面，贝茜移动到位置$k+1$.（正反面的概率各是$\\frac {1}{2}$）\n</p>\n<p>\n2. 从平衡木上跳下来并且获得收入$f(k)$$(0&lt;=f(k)&lt;=10^9)$\n</p>\n<p>\n因为移动取决于随机投掷硬币，贝茜意识到她不能保证任何特定的收入。然而，根据贝茜开始的位置，她想知道获得收入的最高期望(通过最合适的策略)。比如说，如果她的策略将会有$\\frac {1}{2}$的机率赚到$10$块钱，$\\frac {1}{4}$的机率赚到$8$块钱，$\\frac {1}{2}$的机率赚到$0$块钱，那么她的收入期望将会是加权平均数$10(1/2)+8(1/4)+0(1/4)=7$。\n</p>\n<h3>\n【输入格式】\n</h3>\n<p>\n第一行包含一个正整数$N$。剩下的N行包含$f(1)...f(N)$\n</p>\n<h3>\n【输出格式】\n</h3>\n<p>\n输出$N$行，第$i$行四舍五入到收入的$10^5$倍\n</p>\n<h3>\n【样例输入】\n</h3>\n<pre>2\n1\n3</pre>\n<h3>\n【样例输出】\n</h3>\n<pre>150000 \n300000</pre>\n<h3>\n【提示】\n</h3>\n<p>\n$N/A$\n</p>\n<p>\n与标准答案差1以内即可通过\n</p>\n<h3>\n【来源】\n</h3>\n<p>\nhttp://www.usaco.org/index.php?page=viewproblem2&amp;cpid=864\n</p>\n<p>\nUSACO Dec 2018 Platinum Division\n</p>\n\n"}]}