{"title":"[HAOI2004模拟] 数列问题","time_limit":1000,"memory_limit":128,"url":"http://cogs.pro:8080/cogs/problem/problem.php?pid=lxSzyxxee","statement":[{"title":"# 题目描述","format":"html","require":["katex"],"content":"\n\n<p>\n\t<span style=\"font-family:宋体;\"><b>问题描述</b><br/>\n</span>试编程将 1 至 N （ N ≤ 15 ）的自然数序列 1 ， 2 ， … ， N 重新排列，使任意相邻两数之和为素数。例如 N=3 时有两种排列方案 123 、 321 满足要求。\n</p>\n<p align=\"left\">\n\t【输入格式】\n</p>\n<p style=\"text-indent:21pt;\">\n\t<span style=\"font-family:宋体;\">输入文件：dfs3.in</span>\n</p>\n<p style=\"text-indent:21pt;\">\n\t第一行：一个整数n(1&lt;=n&lt;=15)\n</p>\n<p>\n\t<span></span>【输出格式】\n</p>\n<p style=\"text-indent:21pt;\">\n\t<span style=\"font-family:宋体;\">输出文件：dfs3.out</span>\n</p>\n<p style=\"text-indent:21pt;font-family:&#39;宋体&#39;;\">\n\t输出若干行，每行为一种排列方案（排列方案按字典序排列， 相邻数字之间用空格分隔） ），最后一行输出排列方案总数。\n</p>\n<p>\n\t【输入样例】\n</p>\n<p>\n\t输入文件名：<span><span>dfs3.in</span></span>\n</p>\n<p>\n\t3\n</p>\n<p>\n\t输出文件名：<span><span>dfs3.out</span></span>\n</p>\n<p>\n\t1 2 3<br/>\n3 2 1<br/>\n2\n</p>\n\n"}]}