{"title":"谁是组长","time_limit":1000,"memory_limit":10,"url":"http://www.joyoi.cn/problem/tyvj-3286","statement":[{"title":"","format":"markdown","require":["katex"],"content":"\n# \n\n \n # 题目描述 \n<p>\n谁是组长\r<br>\r<br>问题描述：\r<br>　　八中信息组需要选一个组长。信息组一共有n个人，分别用1到n编号，其中m个人参与了投票。得票数过半（票数大于m div 2）的人将被选为组长。\r<br>　　输入数据将告知这m个人分别将票投给了谁，请统计出谁将担任八中信息组的组长。\r<br></p> \n\n \n # 输入格式 \n<p>\n　　第一行两个数n和m。\r<br>　　第二行有m个数，这些数都是不超过n的正整数，表明这m个人的选择。\r<br>\r<br></p> \n\n \n # 输出格式 \n<p>\n　　输出将被选为组长的人。如果没有人的票数过半，请输出-1。\r<br>\r<br></p> \n\n \n # 提示 \n<p>\n时间限制：\r<br>　　各测试点1秒。\r<br>\r<br>内存限制：\r<br>　　你的程序将被分配10MB的运行空间。\r<br>\r<br>数据规模：\r<br>    1 <= n <= maxlongint\r<br>    1 <= m <= 10000\r<br></p> "},{"title":"# 样例数据","format":"markdown","require":["katex"],"content":"<style>\n        table,table tr th, table tr td { border:1px solid #0094ff; }\n        table { width: 200px; min-height: 25px; line-height: 25px; text-align: center; border-collapse: collapse;}   \n    </style>\n<table>\n\t<tr>\n\t\t<td>输入样例</td>\n\t\t<td>输出样例</td>\n\t</tr>\n<tr><td>7 4\r\n7 7 2 7\r\n\r\n</td><td>7\r\n\r</td></tr></table>\n\n"}]}