{"title":"一元N次方程","time_limit":1000,"memory_limit":64,"url":"http://www.joyoi.cn/problem/tyvj-3907","statement":[{"title":"","format":"markdown","require":["katex"],"content":"\n# \n\n \n # 题目描述 \n<p>解一元N次方程。</p>\r\n\r\n<p>每个系数已化到整数（2^30以内），最简。</p>\r\n\r\n<p>等式右边为0.</p>\r\n\r\n<p>输出所有的实数根即可。</p>\r\n\r\n<p>保留6位小数。</p>\r\n\r\n<p>字母为小写的x</p>\r\n\r\n<p>&nbsp;</p>\r\n\r\n<p>样例输入：</p>\r\n\r\n<p>x^2-3x+2=0</p>\r\n\r\n<p>样例输出：</p>\r\n\r\n<p>x1=1</p>\r\n\r\n<p>x2=2</p>\r\n\r\n<p>&nbsp;</p> \n\n \n # 输入格式 \n<p>一行。输入方程。</p> \n\n \n # 输出格式 \n<p>x1=...</p>\r\n\r\n<p>x2=...</p>\r\n\r\n<p>...</p>\r\n\r\n<p>注意：输出的x1&nbsp;x2&nbsp;...&nbsp;xn各不相同，且从小到大输出。</p> \n\n"}]}