{"title":"数字串","time_limit":1000,"memory_limit":128,"url":"http://www.joyoi.cn/problem/tyvj-1063","statement":[{"title":"","format":"markdown","require":["katex"],"content":"\n# \n\n \n # 题目描述 \n给你一个长度为n的数字串，数字串里会包含1-m这些数字。如果连续的一段数字子串包含了1-m这些数字，则称这个数字字串为NUM串。你的任务是求出长度最短的NUM串是什么，只需要输出这个长度即可。<BR>1&lt;=n，m&lt;=200000 \n\n \n # 输入格式 \n第一行给定n和m。&nbsp;<BR>第二行n个数，表示数字串，数字间用空格隔开。<BR> \n\n \n # 输出格式 \n如果存在NUM串则输出最短NUM串长度，否则输出“NO”。 "},{"title":"样例数据","format":"markdown","require":["katex"],"content":"<style>\n        table,table tr th, table tr td { border:1px solid #0094ff; }\n        table { width: 200px; min-height: 25px; line-height: 25px; text-align: center; border-collapse: collapse;}   \n    </style>\n<table>\n\t<tr>\n\t\t<td>输入样例</td>\n\t\t<td>输出样例</td>\n\t</tr>\n<tr><td>5 3\r\n1 2 2 3 1\r\n</td><td>3\r\n</td></tr></table>\n\n"}]}